mglairflowutilslib/__init__.py
mglairflowutilslib/mysql_mgr.py
mglairflowutilslib/utilslib.py
mglairflowutilslib-1.0.39.dist-info/LICENSE
mglairflowutilslib-1.0.39.dist-info/METADATA
mglairflowutilslib-1.0.39.dist-info/WHEEL
mglairflowutilslib-1.0.39.dist-info/top_level.txt
mglairflowutilslib-1.0.39.dist-info/RECORD
