Metadata-Version: 2.1
Name: mglairflowutilslib
Version: 1.0.39
Summary: Library for simplify third party request
Home-page: https://github.com/medigaplife/mgl-airflow-utilslib
Author: Medigap Life
Author-email: ankur.vyas@marutitech.com
Project-URL: Bug Tracker, https://github.com/medigaplife/mgl-airflow-utilslib/issues
Classifier: Programming Language :: Python :: 3
Classifier: License :: OSI Approved :: MIT License
Classifier: Operating System :: OS Independent
Requires-Python: >=3.6
License-File: LICENSE
